Metadata-Version: 2.1
Name: steamid-social-auth-core
Version: 5.0.0
Summary: Python social authentication with steamid.
Home-page: https://github.com/python-social-auth/social-core
Author: Minh Le
Author-email: leduyminh48@gmail.com
License: BSD
Keywords: openid,oauth,saml,social auth
Platform: UNKNOWN
Classifier: Development Status :: 4 - Beta
Classifier: Topic :: Internet
Classifier: License :: OSI Approved :: BSD License
Classifier: Intended Audience :: Developers
Classifier: Environment :: Web Environment
Classifier: Programming Language :: Python
Classifier: Programming Language :: Python :: 2
Classifier: Programming Language :: Python :: 2.7
Classifier: Programming Language :: Python :: 3
Classifier: Programming Language :: Python :: 3.5
Classifier: Programming Language :: Python :: 3.6
Classifier: Programming Language :: Python :: 3.7
Provides-Extra: openidconnect
Provides-Extra: saml
Provides-Extra: azuread
Provides-Extra: all
Provides-Extra: allpy2
Provides-Extra: allpy3
